README.md
setup.cfg
setup.py
vazio/__init__.py
vazio/variandual.py
vazio.egg-info/PKG-INFO
vazio.egg-info/SOURCES.txt
vazio.egg-info/dependency_links.txt
vazio.egg-info/entry_points.txt
vazio.egg-info/requires.txt
vazio.egg-info/top_level.txt
vazio.egg-info/zip-safe
vazio/protocol/__init__.py
vazio/protocol/multigauge.py
vazio/simulator/__init__.py
vazio/simulator/agilent.py
vazio/simulator/mks.py
vazio/simulator/variandual.py